releasemanager/__init__.py
releasemanager/__version__.py
releasemanager/admin.py
releasemanager/apps.py
releasemanager/models.py
releasemanager/settings.py
releasemanager/tests.py
releasemanager/urls.py
releasemanager/views.py
releasemanager/api/serializers.py
releasemanager/api/urls.py
releasemanager/api/views.py
releasemanager/management/commands/__init__.py
releasemanager/management/commands/rmaddfile.py
releasemanager/management/commands/rmaddrelease.py
releasemanager/management/commands/rmpackages.py
releasemanager/migrations/0001_initial.py
releasemanager/migrations/__init__.py
releasemanager/templates/releasemanager/base.html
releasemanager/templates/releasemanager/index.html
releasemanager/templates/releasemanager/list_releases.html
releasemanager/templates/releasemanager/package_releases.html
releasemanager/templates/releasemanager/release_template.html
releasemanager/templatetags/__init__.py
releasemanager/templatetags/release_template_tags.py
django_release_manager-0.1.2.dist-info/METADATA
django_release_manager-0.1.2.dist-info/WHEEL
django_release_manager-0.1.2.dist-info/top_level.txt
django_release_manager-0.1.2.dist-info/RECORD
