Metadata-Version: 2.1
Name: django-release-manager
Version: 0.1.2
Summary: A Release Manager for Embedded Apps in your website, such as an SPA.
Author-email: Grant Viklund <renderbox@gmail.com>
Project-URL: Homepage, https://github.com/renderbox/django-release-manager/
Project-URL: Bug Tracker, https://github.com/renderbox/django-release-manager//issues
Keywords: django,app
Classifier: Development Status :: 2 - Pre-Alpha
Classifier: Intended Audience :: Developers
Classifier: Programming Language :: Python :: 3 :: Only
Classifier: License :: OSI Approved :: MIT License
Classifier: Operating System :: OS Independent
Requires-Python: >=3.7
Requires-Dist: Django <4.2,>=3.0
Requires-Dist: djangorestframework
Requires-Dist: django-cors-headers
Provides-Extra: dev
Requires-Dist: django-crispy-forms ; extra == 'dev'
Requires-Dist: crispy-bootstrap5 ; extra == 'dev'
Requires-Dist: django-allauth ; extra == 'dev'
Requires-Dist: django-extensions ; extra == 'dev'
Requires-Dist: black ; extra == 'dev'
Requires-Dist: flake8 ; extra == 'dev'
Requires-Dist: flake8-black ; extra == 'dev'
Requires-Dist: mypy ; extra == 'dev'
Requires-Dist: bandit ; extra == 'dev'
Requires-Dist: isort ; extra == 'dev'
Requires-Dist: toml ; extra == 'dev'
Provides-Extra: docs
Requires-Dist: django-extensions ; extra == 'docs'
Requires-Dist: coverage ; extra == 'docs'
Provides-Extra: test
Requires-Dist: coverage ; extra == 'test'
